async_bing_client/__init__.py
async_bing_client/client.py
async_bing_client/const.py
async_bing_client/type.py
async_bing_client/utils.py
async_bing_client-0.1.6.dist-info/METADATA
async_bing_client-0.1.6.dist-info/WHEEL
async_bing_client-0.1.6.dist-info/RECORD
