Metadata-Version: 2.1
Name: async-bing-client
Version: 0.1.6
Summary: Async Client for Newbing.
Home-page: https://github.com/canxin121/Async-Bing-Client
Author: canxin
Author-email: 1969730106@qq.com
Requires-Python: >=3.8,<4.0
Classifier: Programming Language :: Python :: 3
Classifier: Programming Language :: Python :: 3.8
Classifier: Programming Language :: Python :: 3.9
Classifier: Programming Language :: Python :: 3.10
Classifier: Programming Language :: Python :: 3.11
Requires-Dist: aiohttp[socks] (>=3.8.5,<4.0.0)
Requires-Dist: certifi (>=2023.7.22,<2024.0.0)
Requires-Dist: loguru (>=0.7.0,<0.8.0)
Requires-Dist: pillow (>=10.0.0,<11.0.0)
Requires-Dist: pydantic (>=1.10.12,<2.0.0)
Requires-Dist: regex (>=2023.8.8,<2024.0.0)
